mormo/__init__.py
mormo/api.py
mormo/cli.py
mormo/convert.py
mormo/model.py
mormo/postman_test.py
mormo/schema/__init__.py
mormo/schema/api.py
mormo/schema/openapi_v3.py
mormo/schema/postman_collection_v2.py
mormo/util.py
mormo-0.7.47.dist-info/entry_points.txt
mormo-0.7.47.dist-info/LICENSE
mormo-0.7.47.dist-info/WHEEL
mormo-0.7.47.dist-info/METADATA
mormo-0.7.47.dist-info/RECORD
